{
  "updatedAt": "2026-04-29T22:29:47Z",
  "gold": {
    "symbol": "GC=F",
    "price": 4562.0,
    "previousClose": 4591.5,
    "change": -29.5,
    "changePercent": -0.64,
    "dayHigh": 4562.4,
    "dayLow": 4550.8,
    "date": "2026-04-29"
  },
  "silver": {
    "symbol": "SI=F",
    "price": 71.94,
    "previousClose": 73.21,
    "change": -1.26,
    "changePercent": -1.72,
    "dayHigh": 71.98,
    "dayLow": 71.65,
    "date": "2026-04-29"
  },
  "oil": {
    "symbol": "CL=F",
    "price": 107.97,
    "previousClose": 99.93,
    "change": 8.04,
    "changePercent": 8.05,
    "dayHigh": 109.64,
    "dayLow": 107.58,
    "date": "2026-04-29"
  },
  "bitcoin": {
    "symbol": "BTC-USD",
    "price": 75814.0,
    "previousClose": 76350.67,
    "change": -536.67,
    "changePercent": -0.7,
    "dayHigh": 77881.66,
    "dayLow": 75018.95,
    "date": "2026-04-29"
  },
  "sp500": {
    "symbol": "^GSPC",
    "price": 7135.95,
    "previousClose": 7138.8,
    "change": -2.85,
    "changePercent": -0.04,
    "dayHigh": 7145.63,
    "dayLow": 7107.86,
    "date": "2026-04-29"
  }
}