{
  "updatedAt": "2026-06-03T23:17:14Z",
  "gold": {
    "symbol": "GC=F",
    "price": 4475.3,
    "previousClose": 4489.1,
    "change": -13.8,
    "changePercent": -0.31,
    "dayHigh": 4479.2,
    "dayLow": 4450.1,
    "date": "2026-06-03"
  },
  "silver": {
    "symbol": "SI=F",
    "price": 73.31,
    "previousClose": 75.31,
    "change": -2.0,
    "changePercent": -2.66,
    "dayHigh": 73.46,
    "dayLow": 72.57,
    "date": "2026-06-03"
  },
  "oil": {
    "symbol": "CL=F",
    "price": 95.26,
    "previousClose": 93.76,
    "change": 1.5,
    "changePercent": 1.6,
    "dayHigh": 95.91,
    "dayLow": 95.0,
    "date": "2026-06-03"
  },
  "bitcoin": {
    "symbol": "BTC-USD",
    "price": 64416.77,
    "previousClose": 66703.66,
    "change": -2286.89,
    "changePercent": -3.43,
    "dayHigh": 67390.91,
    "dayLow": 64388.75,
    "date": "2026-06-03"
  },
  "sp500": {
    "symbol": "^GSPC",
    "price": 7553.68,
    "previousClose": 7609.78,
    "change": -56.1,
    "changePercent": -0.74,
    "dayHigh": 7605.35,
    "dayLow": 7551.22,
    "date": "2026-06-03"
  }
}